sweetener/__init__.py
sweetener/ansicodes.py
sweetener/clazz.py
sweetener/collections.py
sweetener/colors.py
sweetener/common.py
sweetener/compare.py
sweetener/decorators.py
sweetener/io.py
sweetener/iterator.py
sweetener/logging.py
sweetener/math.py
sweetener/node.py
sweetener/ops.py
sweetener/quicksort.py
sweetener/record.py
sweetener/serde.py
sweetener/sorting.py
sweetener/stream.py
sweetener/test_node.py
sweetener/test_ops.py
sweetener/test_record.py
sweetener/test_sorting.py
sweetener/test_text.py
sweetener/text.py
sweetener/token.py
sweetener/util.py
sweetener/visual.py
sweetener-0.2.1.dist-info/LICENSE.txt
sweetener-0.2.1.dist-info/METADATA
sweetener-0.2.1.dist-info/WHEEL
sweetener-0.2.1.dist-info/top_level.txt
sweetener-0.2.1.dist-info/RECORD
