Metadata-Version: 2.1
Name: sweetener
Version: 0.2.1
Summary: A base library for writing compilers and interpreters
Home-page: https://github.com/samvv/sweetener
Author: Sam Vervaeck
Author-email: samvv@pm.me
Project-URL: Bug Reports, https://github.com/samvv/sweetener/issues
Project-URL: Source, https://github.com/samvv/sweetener/
Keywords: productivity,algorithms,data-structures,development,programming
Classifier: Development Status :: 4 - Beta
Classifier: Intended Audience :: Developers
Classifier: Topic :: Software Development :: Libraries
Classifier: Topic :: Utilities
Classifier: License :: OSI Approved :: MIT License
Classifier: Programming Language :: Python :: 3
Classifier: Programming Language :: Python :: 3.12
Classifier: Programming Language :: Python :: 3 :: Only
Requires-Python: >=3.12, <4
License-File: LICENSE.txt
Requires-Dist: colorama
Provides-Extra: dev
Provides-Extra: full
Requires-Dist: pyyaml ; extra == 'full'
Requires-Dist: graphviz ; extra == 'full'
Provides-Extra: test
Requires-Dist: pytest ; extra == 'test'
